dhampyr/__init__.py
dhampyr/api.py
dhampyr/builtins.py
dhampyr/config.py
dhampyr/context.py
dhampyr/converter.py
dhampyr/failures.py
dhampyr/requirement.py
dhampyr/util.py
dhampyr/validator.py
dhampyr/variable.py
dhampyr/verifier.py
dhampyr-1.0.2.dist-info/METADATA
dhampyr-1.0.2.dist-info/WHEEL
dhampyr-1.0.2.dist-info/licenses/LICENSE
dhampyr-1.0.2.dist-info/RECORD
