Metadata-Version: 2.4
Name: dhampyr
Version: 1.0.2
Summary: Python simple validator for dict-like objects
Project-URL: Homepage, https://github.com/sozu/py-dhampyr
Author-email: sozuberry <sozuberry@gmail.com>
License-File: LICENSE
Classifier: License :: OSI Approved :: MIT License
Classifier: Operating System :: OS Independent
Classifier: Programming Language :: Python :: 3.9
Requires-Python: >=3.9
Requires-Dist: typing-extensions
